{
  "runId": "l2_shenli_20260709T202051Z_866b59",
  "startRow": 178,
  "endRow": 180,
  "rowCount": 3,
  "attachmentCount": 17,
  "attachmentManifest": [
    {
      "uid": "沈礼_7.10_04",
      "sheetRow": 178,
      "fileName": "附件一_寒武纪_2025年年度报告_20260313.pdf",
      "path": "C:\\Users\\Carbene\\Documents\\GitHub\\AI-Question-Generate\\outputs\\auto_runs\\l2_shenli_20260709T202051Z_866b59\\attachments\\01_finance\\附件一_寒武纪_2025年年度报告_20260313.pdf",
      "relativePath": "attachments/01_finance/附件一_寒武纪_2025年年度报告_20260313.pdf",
      "bytes": 1531788,
      "expectedFormat": "pdf",
      "detectedFormat": "pdf",
      "sha256": "e9360bfb6ad2d66ce7b65da15f8fa2fcdda9fde526e2a76dba3964327507f4ab",
      "validation": "PASS"
    },
    {
      "uid": "沈礼_7.10_04",
      "sheetRow": 178,
      "fileName": "附件二_寒武纪_2024年年度报告_20250419.pdf",
      "path": "C:\\Users\\Carbene\\Documents\\GitHub\\AI-Question-Generate\\outputs\\auto_runs\\l2_shenli_20260709T202051Z_866b59\\attachments\\01_finance\\附件二_寒武纪_2024年年度报告_20250419.pdf",
      "relativePath": "attachments/01_finance/附件二_寒武纪_2024年年度报告_20250419.pdf",
      "bytes": 1505155,
      "expectedFormat": "pdf",
      "detectedFormat": "pdf",
      "sha256": "87f63aad82dc43fd0613de60bb72e3c88fcacffb9e074767c947d4bd76cb4d7b",
      "validation": "PASS"
    },
    {
      "uid": "沈礼_7.10_04",
      "sheetRow": 178,
      "fileName": "附件三_寒武纪_2025年度业绩快报_20260228.pdf",
      "path": "C:\\Users\\Carbene\\Documents\\GitHub\\AI-Question-Generate\\outputs\\auto_runs\\l2_shenli_20260709T202051Z_866b59\\attachments\\01_finance\\附件三_寒武纪_2025年度业绩快报_20260228.pdf",
      "relativePath": "attachments/01_finance/附件三_寒武纪_2025年度业绩快报_20260228.pdf",
      "bytes": 118340,
      "expectedFormat": "pdf",
      "detectedFormat": "pdf",
      "sha256": "5d9ab073fcc76958f7b716eebed15b0a99cf96385155d3b2f87d0f668ba05bb1",
      "validation": "PASS"
    },
    {
      "uid": "沈礼_7.10_04",
      "sheetRow": 178,
      "fileName": "附件四_寒武纪_2026年第一季度报告_20260430.pdf",
      "path": "C:\\Users\\Carbene\\Documents\\GitHub\\AI-Question-Generate\\outputs\\auto_runs\\l2_shenli_20260709T202051Z_866b59\\attachments\\01_finance\\附件四_寒武纪_2026年第一季度报告_20260430.pdf",
      "relativePath": "attachments/01_finance/附件四_寒武纪_2026年第一季度报告_20260430.pdf",
      "bytes": 189239,
      "expectedFormat": "pdf",
      "detectedFormat": "pdf",
      "sha256": "6aed917a6930c4ffc79d880ac0841c92e62aabc6684f4862129f48a91fed18d0",
      "validation": "PASS"
    },
    {
      "uid": "沈礼_7.10_04",
      "sheetRow": 178,
      "fileName": "附件五_上交所_XBRL经营业绩概览_寒武纪_2022至2025.json",
      "path": "C:\\Users\\Carbene\\Documents\\GitHub\\AI-Question-Generate\\outputs\\auto_runs\\l2_shenli_20260709T202051Z_866b59\\attachments\\01_finance\\附件五_上交所_XBRL经营业绩概览_寒武纪_2022至2025.json",
      "relativePath": "attachments/01_finance/附件五_上交所_XBRL经营业绩概览_寒武纪_2022至2025.json",
      "bytes": 4339,
      "expectedFormat": "json",
      "detectedFormat": "json",
      "sha256": "b0e19871f54c9f685f306f0a8c3ed3ce7db885ee43db51b0c37d7c6ad5c49504",
      "validation": "PASS"
    },
    {
      "uid": "沈礼_7.10_05",
      "sheetRow": 179,
      "fileName": "附件一_消费型锂电池货物铁路运输指导意见.html",
      "path": "C:\\Users\\Carbene\\Documents\\GitHub\\AI-Question-Generate\\outputs\\auto_runs\\l2_shenli_20260709T202051Z_866b59\\attachments\\02_logistics\\附件一_消费型锂电池货物铁路运输指导意见.html",
      "relativePath": "attachments/02_logistics/附件一_消费型锂电池货物铁路运输指导意见.html",
      "bytes": 57848,
      "expectedFormat": "html",
      "detectedFormat": "html",
      "sha256": "b6a4712ed28a1c223f7cf407e0c1ee093bf35ccae18a51b97c9281379774324f",
      "validation": "PASS"
    },
    {
      "uid": "沈礼_7.10_05",
      "sheetRow": 179,
      "fileName": "附件二_铁路危险货物运输安全监督管理规定.html",
      "path": "C:\\Users\\Carbene\\Documents\\GitHub\\AI-Question-Generate\\outputs\\auto_runs\\l2_shenli_20260709T202051Z_866b59\\attachments\\02_logistics\\附件二_铁路危险货物运输安全监督管理规定.html",
      "relativePath": "attachments/02_logistics/附件二_铁路危险货物运输安全监督管理规定.html",
      "bytes": 102928,
      "expectedFormat": "html",
      "detectedFormat": "html",
      "sha256": "de352ab387fda1d18d97e1dea96e8567cdb24121b9b8d1f451cf4eceb1a1c536",
      "validation": "PASS"
    },
    {
      "uid": "沈礼_7.10_05",
      "sheetRow": 179,
      "fileName": "附件三_铁路货物运输规则_2026.pdf",
      "path": "C:\\Users\\Carbene\\Documents\\GitHub\\AI-Question-Generate\\outputs\\auto_runs\\l2_shenli_20260709T202051Z_866b59\\attachments\\02_logistics\\附件三_铁路货物运输规则_2026.pdf",
      "relativePath": "attachments/02_logistics/附件三_铁路货物运输规则_2026.pdf",
      "bytes": 339815,
      "expectedFormat": "pdf",
      "detectedFormat": "pdf",
      "sha256": "79eb3d7ec4839e2e327aad285b395e850a2510ff5a58381253be33b40586f6b6",
      "validation": "PASS"
    },
    {
      "uid": "沈礼_7.10_05",
      "sheetRow": 179,
      "fileName": "附件四_国际货协危险货物规则2025修改通知.html",
      "path": "C:\\Users\\Carbene\\Documents\\GitHub\\AI-Question-Generate\\outputs\\auto_runs\\l2_shenli_20260709T202051Z_866b59\\attachments\\02_logistics\\附件四_国际货协危险货物规则2025修改通知.html",
      "relativePath": "attachments/02_logistics/附件四_国际货协危险货物规则2025修改通知.html",
      "bytes": 47005,
      "expectedFormat": "html",
      "detectedFormat": "html",
      "sha256": "dda0477da325f9f66cb85cc4ae04a44fb4469f7b0484e5f78565d95027e0a024",
      "validation": "PASS"
    },
    {
      "uid": "沈礼_7.10_05",
      "sheetRow": 179,
      "fileName": "附件五_国际货协危险货物规则2025修改事项.pdf",
      "path": "C:\\Users\\Carbene\\Documents\\GitHub\\AI-Question-Generate\\outputs\\auto_runs\\l2_shenli_20260709T202051Z_866b59\\attachments\\02_logistics\\附件五_国际货协危险货物规则2025修改事项.pdf",
      "relativePath": "attachments/02_logistics/附件五_国际货协危险货物规则2025修改事项.pdf",
      "bytes": 592757,
      "expectedFormat": "pdf",
      "detectedFormat": "pdf",
      "sha256": "ef5af4a280f01da2fcad9df1aa6c94e2fbb11dc27530f438bf608b833d39f202",
      "validation": "PASS"
    },
    {
      "uid": "沈礼_7.10_05",
      "sheetRow": 179,
      "fileName": "附件六_B3原型样机订舱事实与缺件清单_截至2026-07-10.json",
      "path": "C:\\Users\\Carbene\\Documents\\GitHub\\AI-Question-Generate\\outputs\\auto_runs\\l2_shenli_20260709T202051Z_866b59\\attachments\\02_logistics\\附件六_B3原型样机订舱事实与缺件清单_截至2026-07-10.json",
      "relativePath": "attachments/02_logistics/附件六_B3原型样机订舱事实与缺件清单_截至2026-07-10.json",
      "bytes": 5006,
      "expectedFormat": "json",
      "detectedFormat": "json",
      "sha256": "7cb6d7d57136d4bac5eef448882982459919a1c9ca07ca06b5ddd51bd590284a",
      "validation": "PASS"
    },
    {
      "uid": "沈礼_7.10_06",
      "sheetRow": 180,
      "fileName": "附件一_华东理工大学LC20A采购技术参数公示.html",
      "path": "C:\\Users\\Carbene\\Documents\\GitHub\\AI-Question-Generate\\outputs\\auto_runs\\l2_shenli_20260709T202051Z_866b59\\attachments\\03_lab\\附件一_华东理工大学LC20A采购技术参数公示.html",
      "relativePath": "attachments/03_lab/附件一_华东理工大学LC20A采购技术参数公示.html",
      "bytes": 50872,
      "expectedFormat": "html",
      "detectedFormat": "html",
      "sha256": "5220debb43d386a378d5769e3d66de43cd0a2541d9bf086ab215bbe392ed6b51",
      "validation": "PASS"
    },
    {
      "uid": "沈礼_7.10_06",
      "sheetRow": 180,
      "fileName": "附件二_岛津LC20A安装准备条件.pdf",
      "path": "C:\\Users\\Carbene\\Documents\\GitHub\\AI-Question-Generate\\outputs\\auto_runs\\l2_shenli_20260709T202051Z_866b59\\attachments\\03_lab\\附件二_岛津LC20A安装准备条件.pdf",
      "relativePath": "attachments/03_lab/附件二_岛津LC20A安装准备条件.pdf",
      "bytes": 301277,
      "expectedFormat": "pdf",
      "detectedFormat": "pdf",
      "sha256": "b9043c28906c83277d82204f39de10f9ee8970da6dc78e4d1e1683800955eb7f",
      "validation": "PASS"
    },
    {
      "uid": "沈礼_7.10_06",
      "sheetRow": 180,
      "fileName": "附件三_中国地质大学大型仪器设备验收工作流程.pdf",
      "path": "C:\\Users\\Carbene\\Documents\\GitHub\\AI-Question-Generate\\outputs\\auto_runs\\l2_shenli_20260709T202051Z_866b59\\attachments\\03_lab\\附件三_中国地质大学大型仪器设备验收工作流程.pdf",
      "relativePath": "attachments/03_lab/附件三_中国地质大学大型仪器设备验收工作流程.pdf",
      "bytes": 288127,
      "expectedFormat": "pdf",
      "detectedFormat": "pdf",
      "sha256": "6d376734b5a08d8e8b667273b30d626dca7bdb37d56dc2c7a563f1dd224b99f2",
      "validation": "PASS"
    },
    {
      "uid": "沈礼_7.10_06",
      "sheetRow": 180,
      "fileName": "附件四_中国传媒大学项目到货验收申请表.xlsx",
      "path": "C:\\Users\\Carbene\\Documents\\GitHub\\AI-Question-Generate\\outputs\\auto_runs\\l2_shenli_20260709T202051Z_866b59\\attachments\\03_lab\\附件四_中国传媒大学项目到货验收申请表.xlsx",
      "relativePath": "attachments/03_lab/附件四_中国传媒大学项目到货验收申请表.xlsx",
      "bytes": 11214,
      "expectedFormat": "xlsx",
      "detectedFormat": "xlsx",
      "sha256": "f60c4966e0a5ed73f7c124411c8e9c662bfc1b8ebbfb60c38ae97f018135e538",
      "validation": "PASS"
    },
    {
      "uid": "沈礼_7.10_06",
      "sheetRow": 180,
      "fileName": "附件五_华南理工大学仪器设备开箱与点验货记录.docx",
      "path": "C:\\Users\\Carbene\\Documents\\GitHub\\AI-Question-Generate\\outputs\\auto_runs\\l2_shenli_20260709T202051Z_866b59\\attachments\\03_lab\\附件五_华南理工大学仪器设备开箱与点验货记录.docx",
      "relativePath": "attachments/03_lab/附件五_华南理工大学仪器设备开箱与点验货记录.docx",
      "bytes": 42496,
      "expectedFormat": "docx",
      "detectedFormat": "docx",
      "sha256": "4ab58a62b2ae793d713825ed23f8b225cf24e997a9339a75a0cc1d97c2fdfcab",
      "validation": "PASS"
    },
    {
      "uid": "沈礼_7.10_06",
      "sheetRow": 180,
      "fileName": "附件六_华南理工大学进口仪器设备购置合同模板.docx",
      "path": "C:\\Users\\Carbene\\Documents\\GitHub\\AI-Question-Generate\\outputs\\auto_runs\\l2_shenli_20260709T202051Z_866b59\\attachments\\03_lab\\附件六_华南理工大学进口仪器设备购置合同模板.docx",
      "relativePath": "attachments/03_lab/附件六_华南理工大学进口仪器设备购置合同模板.docx",
      "bytes": 30239,
      "expectedFormat": "docx",
      "detectedFormat": "docx",
      "sha256": "013ef4caf7b741141b8fb5128bcf93efbe0748885c31fad4233437633043b558",
      "validation": "PASS"
    }
  ]
}
