{
  "schemaVersion": 1,
  "runId": "rewrite_peiying_all_20260709T215207Z_75bdf9",
  "rows": [
    {
      "slot": 1,
      "profileIndex": 0,
      "uid": "獒당＼_7.9_03",
      "sheetRow": 147
    },
    {
      "slot": 2,
      "profileIndex": 1,
      "uid": "獒당＼_7.9_04",
      "sheetRow": 148
    },
    {
      "slot": 3,
      "profileIndex": 2,
      "uid": "獒당＼_7.9_02",
      "sheetRow": 146
    },
    {
      "slot": 4,
      "profileIndex": 3,
      "uid": "獒당＼_7.9_01",
      "sheetRow": 145
    },
    {
      "slot": 5,
      "profileIndex": 4,
      "uid": "獒당＼_7.9_05",
      "sheetRow": 149
    }
  ]
}
