{
  "generatedAt": "2026-07-10T04:19:10.290Z",
  "apply": true,
  "transport": "auto",
  "target": {
    "spreadsheetToken": "ByAysb2Cdh9V2wtISbJc6Z01nwc",
    "sheetId": "49e351",
    "wikiNode": null,
    "meta": null
  },
  "planPath": "C:\\Users\\Carbene\\Documents\\GitHub\\AI-Question-Generate\\outputs\\auto_runs\\rewrite_peiying_natural_reset_20260710\\feishu\\feishu_fill_plan_natural_reset.json",
  "rows": [
    146,
    148
  ],
  "valueRangeCount": 10,
  "skipped": [],
  "valueRanges": [
    {
      "range": "49e351!B146:B146",
      "values": [
        [
          "当前是2026年7月10日，销售明天要在客户周会上说明，官网预约试用、展会扫码和公众号留资产生的线索，能否提出一个少字段海外CRM试点方案。拟议字段包括姓名、手机号、公司邮箱、职位、采购预算和跟进备注。业务希望尽快把三条线索渠道接进统一系统，法务这轮不选择最终出境路径，也不接入真实线索，只判断少字段试点是否值得进入下一轮正式评审，以及会上能承诺到哪一步。\n\n当前拿到的材料只有字段清单、供应商标准合同和一页“全球合规”说明。正式CRM合同、完整字段字典、境外接收方及其安全措施说明、用户授权记录和历史导出日志都没有随材料提供，因此供应商宣传不能替代正式约定，也无法据此确认过去是否已经发生过数据导出。三类线索的收集页面、告知内容和后续使用方式也需要分别核对，展会扫码取得的信息不能自然沿用官网或公众号的授权口径。\n\n周会只形成一个结论：少字段试点是否值得进入下一轮正式评审。六个字段的必要性、个人信息属性和收集来源，用来确定建议保留的最小范围；个人信息保护、数据分类分级、安全评估及跨境流动规则，用来列出正式评审前提。是否适用安全评估、标准合同、豁免或其他路径，仍取决于实际处理规模、接收方情况和正式材料，本轮不替审批人选择。\n\n销售周会使用一份Word版初筛说明，内容包括当前能讲到哪一步、少字段试点的前置条件、暂缓同步的字段、需要供应商或业务补充的材料和后续审批动作。Excel字段核对表逐行记录字段、来源渠道、业务用途、现有材料、建议处理、附件依据、补件责任人和复核状态。交付前按三条线索渠道重新走一遍，确认同一字段没有因来源不同而漏掉告知授权问题，也不把标准合同模板或“全球合规”说明写成已经签署和验证的安全证明。"
        ]
      ],
      "address": "B146",
      "field": "题目",
      "chars": 712
    },
    {
      "range": "49e351!G146:G146",
      "values": [
        [
          "核对三类营销线索进入海外CRM的少字段试点条件，区分境内暂存、字段缩减、暂停同步及补件后复核，并给销售稳定的周会口径。"
        ]
      ],
      "address": "G146",
      "field": "任务概括",
      "chars": 59
    },
    {
      "range": "49e351!L146:L146",
      "values": [
        [
          "附件一：《中华人民共和国个人信息保护法》。来源：https://www.cac.gov.cn/2021-08/20/c_1631050028355286.htm。用于核对告知同意、最小必要、敏感个人信息、自动化决策和个人信息出境条件。\n\n附件二：《中华人民共和国数据安全法》。来源：https://www.cac.gov.cn/2021-06/11/c_1624994566919140.htm。用于整理数据分类分级、安全保护义务、重要数据和风险监测要求。\n\n附件三：《数据出境安全评估办法》。来源：https://www.cac.gov.cn/2022-07/07/c_1658811536594644.htm。用于确认哪些情形可能走安全评估、申报材料和评估关注点。\n\n附件四：《促进和规范数据跨境流动规定》。来源：https://www.cac.gov.cn/2024-03/22/c_1712776611775634.htm。用于核对2024年跨境流动便利化、豁免、负面清单和标准合同等路径。\n\n跨境相关规则用于识别需要核对的路径和事实条件；标准合同模板、供应商宣传及留资行为本身不等同于正式合同、接收方安全材料或用户授权。"
        ]
      ],
      "address": "L146",
      "field": "附件内容",
      "chars": 515
    },
    {
      "range": "49e351!N146:N146",
      "values": [
        [
          "Word版《海外CRM线索同步初筛说明》供销售和法务在客户周会上说明当前判断、试点条件、暂缓字段及后续审批动作。Excel《线索字段与材料核对表》按渠道和字段记录业务用途、当前材料、建议处理、附件依据、补件责任人和复核状态。"
        ]
      ],
      "address": "N146",
      "field": "产物内容",
      "chars": 112
    },
    {
      "range": "49e351!O146:O146",
      "values": [
        [
          "1. 分别还原官网预约试用、展会扫码和公众号留资的收集页面、字段来源及后续流转。\n2. 为姓名、手机号、公司邮箱、职位、采购预算和跟进备注记录业务用途与最小必要性。\n3. 核对三条渠道各自的告知内容和授权记录，不在渠道之间直接沿用授权结论。\n4. 依据个人信息保护和数据安全规则检查个人信息属性、分类分级与境外提供前置条件。\n5. 依据安全评估及跨境流动规则整理可能适用的路径和所需事实条件。\n6. 区分字段清单、供应商标准合同、宣传说明、正式合同和接收方安全材料的效力。\n7. 在未取得实际处理规模和接收方情况时，将相关门槛判断保留为待核，不预设出境路径。\n8. 按境内暂存、减少字段后再讨论、暂停同步和补件后复核安排字段处理建议。\n9. 完成Word初筛说明和Excel字段核对表，写明每项补件的提供方及后续复核动作。\n10. 按三条线索渠道重新演练一次，确认同一字段的告知授权、处理建议和材料状态前后一致，标准合同模板也没有被写成已签署合同。"
        ]
      ],
      "address": "O146",
      "field": "做题关键步骤",
      "chars": 424
    },
    {
      "range": "49e351!B148:B148",
      "values": [
        [
          "当前是2026年7月10日，招聘产品周五要过一次上线评审。后台样式已经把候选人分成A档优先展示、B档抽看、C档沉底，产品打算在7月先做小范围灰度；HR最担心的是C档简历会不会从日常工作里消失，法务关心的则是候选人在投递时能否知道AI参与了初筛，以及被分错后有没有人工处理入口。现在的页面草稿能够说明产品准备怎么做，却没有回答谁对录用判断负责。\n\n候选人从填写简历、提交联系方式，到系统解析经历、生成分档、HR查看和后续通知，沿途会使用手机号、学历、行业、薪资期望等信息。每个字段为什么进入筛选、AI输出会显示在哪里、HR能否看到全部简历、人工改档后旧标签如何处理，都需要在评审中说明。尤其是C档沉底：如果HR默认看不到，所谓“辅助筛选”可能已经变成实际淘汰；如果全部简历仍可检索和恢复，还要明确谁负责抽查、纠错和留痕。\n\n现有四份附件可以用来核对招聘服务、个人信息处理、算法推荐和生成式AI的一般要求。算法参数、训练数据来源、候选人告知或授权记录、人工复核日志尚未提供，因此准确率、公平性和实际复核覆盖率都没有事实基础。评审需要在保留三档但全量可见、把分档改成普通辅助标签、取消C档沉底或暂缓自动分档之间作出当前选择，并把恢复简历、申诉更正、停止灰度的操作落实到具体岗位。\n\n会议靠后使用一份Word评审意见，直接写推荐做法、页面和后台要改的地方、HR人工动作、候选人补救方式及启动条件；Excel表按投递、解析、分档、查看、复核和通知记录使用字段、系统动作、候选人提示、负责人及验证结果。页面草图保留为设计输入，未取得的算法、训练数据、授权和复核记录维持未核验。"
        ]
      ],
      "address": "B148",
      "field": "题目",
      "chars": 682
    },
    {
      "range": "49e351!G148:G148",
      "values": [
        [
          "围绕AI简历分档是否适合进入7月灰度，检查候选人告知、HR可见性、人工纠错和停止机制并形成当前方案。"
        ]
      ],
      "address": "G148",
      "field": "任务概括",
      "chars": 50
    },
    {
      "range": "49e351!L148:L148",
      "values": [
        [
          "附件一：《网络招聘服务管理规定》。来源：https://www.moj.gov.cn/pub/sfbgw/flfggz/flfggzbmgz/202103/t20210309_374224.html。用于核对招聘服务主体责任、招聘信息真实性、求职者信息保护和网络招聘服务规则。\n\n附件二：《中华人民共和国个人信息保护法》。来源：https://www.cac.gov.cn/2021-08/20/c_1631050028355286.htm。用于确认简历字段处理、告知同意、最小必要、自动化决策和敏感信息保护。\n\n附件三：《互联网信息服务算法推荐管理规定》。来源：https://www.cac.gov.cn/2022-01/04/c_1642894606364259.htm。用于整理算法透明度、用户选择权、模型提示和不合理差别待遇风险。\n\n附件四：《生成式人工智能服务管理暂行办法》。来源：https://www.cac.gov.cn/2023-07/13/c_1690898327029107.htm。用于核对训练数据处理、个人信息保护、安全评估和内容治理口径。\n\n这四份规则用于检查招聘流程和候选人权利；后台样式稿仍需算法说明、真实告知页面和人工操作记录配合，才能评价实际运行情况。"
        ]
      ],
      "address": "L148",
      "field": "附件内容",
      "chars": 545
    },
    {
      "range": "49e351!N148:N148",
      "values": [
        [
          "Word评审意见供产品、HR和法务确认推荐方案、页面改动、人工责任、候选人补救及启用条件。Excel流程表按候选人经历记录字段、AI动作、页面提示、HR操作、缺失材料、负责人和验证结果。"
        ]
      ],
      "address": "N148",
      "field": "产物内容",
      "chars": 93
    },
    {
      "range": "49e351!O148:O148",
      "values": [
        [
          "1. 按候选人经历还原简历填写、提交、解析、分档、HR查看、人工复核和结果通知。\n2. 列出每个节点使用的字段、系统输出、页面提示、HR动作及记录位置。\n3. 检查A、B、C三档对排序、可见性和后续联系的实际影响。\n4. 确认误分候选人能否被HR发现、恢复、改档并清除或更正旧标签。\n5. 依据附件核对招聘服务、个人信息、算法推荐和生成内容相关要求。\n6. 把算法参数、训练数据、告知授权和人工复核日志列入上线前待收内容。\n7. 比较全量可见分档、辅助标签、取消C档沉底和暂缓自动分档的利弊。\n8. 形成一项推荐，并明确页面后台改动、人工责任、申诉入口和停止条件。\n9. 完成评审意见和流程表后，从一名被误分的候选人视角走查可见性、纠错、旧标签处理和责任人。"
        ]
      ],
      "address": "O148",
      "field": "做题关键步骤",
      "chars": 329
    }
  ]
}
