{
  "version": 1,
  "generatedAt": "2026-07-09T20:50:23.210Z",
  "sourcePath": "C:\\Users\\Carbene\\Documents\\GitHub\\AI-Question-Generate\\outputs\\auto_runs\\l2_shenli_20260709T202051Z_866b59\\drafts\\l2_questions_178_180_shenli_710.tsv",
  "startRow": 178,
  "count": 3,
  "note": "Use address-box + F2 + clipboard paste for each cell. Do not paste this plan as one block into Feishu.",
  "columnMap": [
    {
      "field": "UID",
      "column": "A"
    },
    {
      "field": "题目",
      "column": "B"
    },
    {
      "field": "任务类型",
      "column": "C"
    },
    {
      "field": "一级目录",
      "column": "D"
    },
    {
      "field": "二级目录",
      "column": "E"
    },
    {
      "field": "三级目录",
      "column": "F"
    },
    {
      "field": "任务概括",
      "column": "G"
    },
    {
      "field": "标注专家工作年限",
      "column": "H"
    },
    {
      "field": "人类完成时间",
      "column": "I"
    },
    {
      "field": "相关附件",
      "column": "J"
    },
    {
      "field": "附件格式",
      "column": "K"
    },
    {
      "field": "附件内容",
      "column": "L"
    },
    {
      "field": "产物格式",
      "column": "M"
    },
    {
      "field": "产物内容",
      "column": "N"
    },
    {
      "field": "做题关键步骤",
      "column": "O"
    },
    {
      "field": "标注专家姓名",
      "column": "P"
    }
  ],
  "rows": [
    {
      "dataRow": 2,
      "sheetRow": 178,
      "title": "复核寒武纪2025年首次盈利的现金含量、营运资金和客户集中度，并据2026年一季报决定是否转入重点研究池。",
      "updates": [
        {
          "address": "A178",
          "column": "A",
          "field": "UID",
          "value": "沈礼_7.10_04",
          "chars": 10,
          "hasNewlines": false,
          "preview": "沈礼_7.10_04"
        },
        {
          "address": "B178",
          "column": "B",
          "field": "题目",
          "value": "投委会下周要决定，寒武纪在2025年首次实现年度盈利后，是从事件跟踪转入重点研究池，还是先保留观察。现在争议不在利润有没有转正，而在利润有没有变成现金：2025年营收和净利润跳升，经营现金流仍为负，前五名客户占比较高，年末应收账款和存货也明显增加；2026年一季报经营现金流转正，但应收账款和预付款继续抬升。请按2026年4月30日可得的公开财务披露统一年度、季度口径，复核业绩快报与年报的一致性，拆出利润到经营现金流的营运资金桥，测算现金含量、应收和存货周转、客户与供应商集中度，并给出“转入重点研究池、保留观察、暂缓”中的一档建议和可量化跟踪阈值。Word写成投委会能直接讨论的研究备忘录，Excel保留原始数据、公式和来源页码；附件没有披露客户名称、订单取消权、逐户回款计划和在手订单质量，结论只落在公开信息可支持的范围内，不外推个别客户信用，也不做目标价。",
          "chars": 382,
          "hasNewlines": false,
          "preview": "投委会下周要决定，寒武纪在2025年首次实现年度盈利后，是从事件跟踪转入重点研究池，还是先保留观察。现在争议不在利润有没有转正，而在利润有没有变成现金：2025"
        },
        {
          "address": "C178",
          "column": "C",
          "field": "任务类型",
          "value": "L2 流程型",
          "chars": 6,
          "hasNewlines": false,
          "preview": "L2 流程型"
        },
        {
          "address": "D178",
          "column": "D",
          "field": "一级目录",
          "value": "投资战略、专业服务与企业经营",
          "chars": 14,
          "hasNewlines": false,
          "preview": "投资战略、专业服务与企业经营"
        },
        {
          "address": "E178",
          "column": "E",
          "field": "二级目录",
          "value": "上市公司经营分析与投前研究",
          "chars": 13,
          "hasNewlines": false,
          "preview": "上市公司经营分析与投前研究"
        },
        {
          "address": "F178",
          "column": "F",
          "field": "三级目录",
          "value": "AI芯片公司盈利质量与营运资金复核",
          "chars": 17,
          "hasNewlines": false,
          "preview": "AI芯片公司盈利质量与营运资金复核"
        },
        {
          "address": "G178",
          "column": "G",
          "field": "任务概括",
          "value": "复核寒武纪2025年首次盈利的现金含量、营运资金和客户集中度，并据2026年一季报决定是否转入重点研究池。",
          "chars": 53,
          "hasNewlines": false,
          "preview": "复核寒武纪2025年首次盈利的现金含量、营运资金和客户集中度，并据2026年一季报决定是否转入重点研究池。"
        },
        {
          "address": "H178",
          "column": "H",
          "field": "标注专家工作年限",
          "value": "5年",
          "chars": 2,
          "hasNewlines": false,
          "preview": "5年"
        },
        {
          "address": "I178",
          "column": "I",
          "field": "人类完成时间",
          "value": "14h",
          "chars": 3,
          "hasNewlines": false,
          "preview": "14h"
        },
        {
          "address": "J178",
          "column": "J",
          "field": "相关附件",
          "value": "附件一_寒武纪_2025年年度报告_20260313.pdf；附件二_寒武纪_2024年年度报告_20250419.pdf；附件三_寒武纪_2025年度业绩快报_20260228.pdf；附件四_寒武纪_2026年第一季度报告_20260430.pdf；附件五_上交所_XBRL经营业绩概览_寒武纪_2022至2025.json",
          "chars": 164,
          "hasNewlines": false,
          "preview": "附件一_寒武纪_2025年年度报告_20260313.pdf；附件二_寒武纪_2024年年度报告_20250419.pdf；附件三_寒武纪_2025年度业绩快报"
        },
        {
          "address": "K178",
          "column": "K",
          "field": "附件格式",
          "value": "pdf, json",
          "chars": 9,
          "hasNewlines": false,
          "preview": "pdf, json"
        },
        {
          "address": "L178",
          "column": "L",
          "field": "附件内容",
          "value": "附件一：《中科寒武纪科技股份有限公司2025年年度报告》（文件：附件一_寒武纪_2025年年度报告_20260313.pdf），属于官方中文资料，用于核对：作为主证据，提取经审计财务数据、客户与供应商集中度、应收账款和存货变动、减值及现金流量表调节项。 来源：https://big5.sse.com.cn/site/cht/www.sse.com.cn/disclosure/listedinfo/announcement/c/new/2026-03-13/688256_20260313_GWH3.pdf。中文摘要：第9、26、30—31、94、97—106、142—146、152—155、178、182、186—187页分别覆盖三年主要财务数据、现金流变动、前五名客户和供应商、审计程序、报表、应收账款、存货、收入、减值和现金流调节。2025年营收6,497,196,198.68元、归母净利润2,059,228,538.67元、经营现金流-498,398,137.01元；前五名客户销售额占88.66%，前五名中四名为本期新增客户；应收账款账面价值670,643,223.27元，同比增长120.17%，存货账面价值4,943,532,510.26元，同比增长178.67%。 证据边界：报告不披露客户名称、逐笔合同、订单取消权、逐户回款计划或在手订单质量；经审计历史数据不能证明未来现金流或个别客户信用。\n附件二：《中科寒武纪科技股份有限公司2024年年度报告》（文件：附件二_寒武纪_2024年年度报告_20250419.pdf），属于官方中文资料，用于核对：建立2024年原始披露基线，核对年报中的营收、亏损、经营现金流、产品结构和直销占比，避免只依赖2025年报告的比较列。 来源：https://big5.sse.com.cn/site/cht/www.sse.com.cn/disclosure/listedinfo/announcement/c/new/2025-04-19/688256_20250419_11FJ.pdf。中文摘要：第10、29—31页覆盖2024年主要会计数据和主营业务结构。2024年营收1,174,464,377.35元、归母净利润-452,338,791.01元、经营现金流-1,617,960,236.90元；云端产品线和直销为主要收入来源。 证据边界：该报告反映截至2024年末的历史情况，不能替代2025年年报或2026年一季报，也不能证明2025年新增客户的持续采购。\n附件三：《中科寒武纪科技股份有限公司2025年度业绩快报公告》（文件：附件三_寒武纪_2025年度业绩快报_20260228.pdf），属于官方中文资料，用于核对：将初步核算的营收、利润和资产数据与3月披露的经审计年报逐项勾稽，记录差异而非默认一致。 来源：https://big5.sse.com.cn/site/cht/www.sse.com.cn/disclosure/listedinfo/announcement/c/new/2026-02-28/688256_20260228_836P.pdf。中文摘要：快报披露2025年营业总收入6,497,196,198.68元、归母净利润2,059,228,538.67元，并明确数据为初步核算、未经审计，最终以年报为准。 证据边界：快报不含完整现金流量表、应收账款、存货明细和客户集中度，且未经审计，只能用于披露时序和数值勾稽。\n附件四：《中科寒武纪科技股份有限公司2026年第一季度报告》（文件：附件四_寒武纪_2026年第一季度报告_20260430.pdf），属于官方中文资料，用于核对：作为年报后的最新定期财务披露，检查经营现金流转正是否伴随应收账款、预付款和存货的改善或转移。 来源：https://big5.sse.com.cn/site/cht/www.sse.com.cn/disclosure/listedinfo/announcement/c/new/2026-04-30/688256_20260430_I4ZK.pdf。中文摘要：一季度营收2,884,696,746.86元、归母净利润1,013,213,581.94元、经营现金流833,967,832.10元；期末应收账款1,219,156,884.63元、预付款项1,896,519,449.47元、存货4,496,708,960.39元。 证据边界：季度报告未经审计，单季数据有季节性且未披露客户结构；不能直接年化，也不能据一季现金流判定全年现金转换已经稳定。\n附件五：《上海证券交易所上市公司经营业绩概览（寒武纪XBRL数据）》（文件：附件五_上交所_XBRL经营业绩概览_寒武纪_2022至2025.json），属于官方中文资料，用于核对：提供可计算的多期结构化字段，作为PDF人工摘录的交叉核验和Excel导入源。 来源：https://query.sse.com.cn/commonSoaQuery.do?isPagination=false&sqlId=COMMON_SSE_PL_XBRL_YJGL_XQ&reportYear=2025,2024,2023,2022&stockId=688256。中文摘要：2025年度记录中，S2020_0010为营业收入649,719.62万元，S2090_0040为净利润205,922.85万元，S2090_0050为扣非净利润176,993.42万元，S2090_0060为经营现金流-49,839.81万元；同一响应还含总资产、总负债和资产负债率。 证据边界：接口只提供概览指标，不含应收账款、存货、客户名单和财务附注；上交所页面提示结构化数据仅供参考，冲突时以对应PDF为准。\n总边界：附件一为寒武纪2025年年度报告，用于提取经审计的营收、利润、现金流、应收账款、存货、减值、客户和供应商集中度；报告显示2025年营业收入64.97亿元、归母净利润20.59亿元，经营活动现金流净额仍为-4.98亿元，前五名客户销售额占88.66%，年末应收账款6.71亿元、存货49.44亿元。附件二为2024年年度报告，用于建立同口径基线并核对2024年原始披露值。附件三为2025年度业绩快报，用于复核初步核算数与后续年报是否一致，快报本身未经审计。附件四为2026年第一季度报告，用于做年报后的最新经营跟踪；一季度经营现金流转为8.34亿元，但期末应收账款12.19亿元、预付款项18.97亿元，季度财务数据未经审计。附件五为上交所上市公司经营业绩概览的XBRL接口原始JSON，提供2022—2025年年度及半年度的结构化营收、利润、经营现金流、总资产、总负债和资产负债率字段；上交所页面明确结构化数据仅供参考，最终以对应PDF为准。资料边界：公开文件未披露客户名称、逐笔合同、订单取消权、在手订单质量、逐户账龄与回款计划，也没有2026年半年度数据，不能据此判断个别客户信用、预测全年现金流或给出目标价。",
          "chars": 2915,
          "hasNewlines": true,
          "preview": "附件一：《中科寒武纪科技股份有限公司2025年年度报告》（文件：附件一_寒武纪_2025年年度报告_20260313.pdf），属于官方中文资料，用于核对：作为"
        },
        {
          "address": "M178",
          "column": "M",
          "field": "产物格式",
          "value": "docx, xlsx",
          "chars": 10,
          "hasNewlines": false,
          "preview": "docx, xlsx"
        },
        {
          "address": "N178",
          "column": "N",
          "field": "产物内容",
          "value": "Word研究备忘录供投委会讨论，结构包括结论卡、快报与年报勾稽、盈利质量判断、利润到经营现金流桥、客户与供应商集中度、2026年一季度跟踪、三档研究池建议、后续核验问题和公开信息边界。Excel测算工作簿至少含来源索引、原始财务数据、口径勾稽、现金转换、营运资金、集中度、季度跟踪和阈值看板；保留单位换算、公式、来源文件与页码，输入区和公式区可区分。验收时能够从任一关键结论回到原始披露，快报与年报差异有记录，年度与季度不混算，缺失的客户名称、合同和回款计划进入待核验清单。",
          "chars": 237,
          "hasNewlines": false,
          "preview": "Word研究备忘录供投委会讨论，结构包括结论卡、快报与年报勾稽、盈利质量判断、利润到经营现金流桥、客户与供应商集中度、2026年一季度跟踪、三档研究池建议、后续"
        },
        {
          "address": "O178",
          "column": "O",
          "field": "做题关键步骤",
          "value": "1. 核对5个附件的发布主体、披露日期、证券代码、文件头和数据期间，建立来源索引并标注年度数据已审计、季度和快报未经审计。\n2. 从2024、2025年报和上交所XBRL JSON提取营收、归母净利润、扣非净利润、经营现金流、总资产和总负债，统一元与万元口径。\n3. 将2025年度业绩快报逐项与2025年报勾稽，记录数值、单位和审计状态差异；冲突时以年报为准。\n4. 提取2024—2025年应收账款、预付款、存货、合同负债、减值损失及主要现金流调节项，检查期初期末与附注是否衔接。\n5. 测算经营现金流/归母净利润、经营现金流/扣非净利润、应收账款占收入、存货占收入、应收周转天数和存货周转天数，并说明平均余额和年末余额口径差异。\n6. 用现金流量表补充资料搭建利润到经营现金流的营运资金桥，拆分存货、经营性应收、经营性应付、折旧摊销、股份支付和减值的方向与影响。\n7. 计算2025年前五名客户、前两名客户、第一大客户及前五名供应商、第一大供应商的集中度，区分报告直接披露值与根据公开金额推算值。\n8. 将2026年一季报与2025年末衔接，检查经营现金流转正、应收账款和预付款增加、存货下降是否同时发生；季度流量只与季度流量比较，期末余额只做时点变化。\n9. 对盈利质量、回款、库存、客户集中和供应链依赖分别给出支持证据、反向证据、缺失信息和置信等级。\n10. 设计“转入重点研究池、保留观察、暂缓”三档判定矩阵，设置未来两个报告期可复核的现金转换、应收增速、库存变化和集中度阈值。\n11. 在Word形成一档建议、关键依据、反例和管理层追问清单，在Excel保留原始数据、公式、单位、来源文件及页码。\n12. 做交叉自检：关键数值能回到附件，快报与年报不混用审计属性，年度与季度不直接年化，未披露的客户名称、合同条件、回款计划和订单质量不作推断。",
          "chars": 778,
          "hasNewlines": true,
          "preview": "1. 核对5个附件的发布主体、披露日期、证券代码、文件头和数据期间，建立来源索引并标注年度数据已审计、季度和快报未经审计。 2. 从2024、2025年报和上交"
        },
        {
          "address": "P178",
          "column": "P",
          "field": "标注专家姓名",
          "value": "沈礼",
          "chars": 2,
          "hasNewlines": false,
          "preview": "沈礼"
        }
      ]
    },
    {
      "dataRow": 3,
      "sheetRow": 179,
      "title": "复核未完成UN38.3的锂电池原型样机及备用电池经中欧班列出运时的申报属性、型号证据、包装标记、鉴定资料和承运确认，形成有边界的订舱放行意见与补件台账。",
      "updates": [
        {
          "address": "A179",
          "column": "A",
          "field": "UID",
          "value": "沈礼_7.10_05",
          "chars": 10,
          "hasNewlines": false,
          "preview": "沈礼_7.10_05"
        },
        {
          "address": "B179",
          "column": "B",
          "field": "题目",
          "value": "截至2026年7月10日，研发负责人想在次日锁一班苏州到华沙的中欧班列舱位：货物是24台运动相机B3工程样机，每台装有1块98Wh锂离子电池，另有8块同型号备用电池；订舱草单却写成了“普通电子产品”。现有UN38.3报告和试验简介只对应已量产的B2电池，B3仍在试验，4箱混装草图也没有说明样机与备用电池分别适用的包装路径；铁路运输条件鉴定、包装检验结论、安全承诺、应急措施以及沿线承运人或主管机关对原型品的接受条件均未提供。业务认为单块不超过100Wh就能先订舱。附件六已把题设货物、路线、包装草图和缺件状态整理成机器可读底表，但不是测试、鉴定或承运批准。请以国际物流合规专员身份做一版docx订舱前放行复核，按“可按现方案提交、补件后再提交、改走危货/原型品路径、暂停出货并确认”给出逐项判断；再用xlsx拆清型号与报告对应、国内段和国际段规则、包件级包装/标记、缺件责任人与承运确认记录。公开资料和题设底表不足以替代当前班列、过境国和承运人的书面接受条件，不能代替他们作最终承运批准。",
          "chars": 445,
          "hasNewlines": false,
          "preview": "截至2026年7月10日，研发负责人想在次日锁一班苏州到华沙的中欧班列舱位：货物是24台运动相机B3工程样机，每台装有1块98Wh锂离子电池，另有8块同型号备用"
        },
        {
          "address": "C179",
          "column": "C",
          "field": "任务类型",
          "value": "L2 流程型",
          "chars": 6,
          "hasNewlines": false,
          "preview": "L2 流程型"
        },
        {
          "address": "D179",
          "column": "D",
          "field": "一级目录",
          "value": "工业制造与供应链",
          "chars": 8,
          "hasNewlines": false,
          "preview": "工业制造与供应链"
        },
        {
          "address": "E179",
          "column": "E",
          "field": "二级目录",
          "value": "物流与危险货物运输",
          "chars": 9,
          "hasNewlines": false,
          "preview": "物流与危险货物运输"
        },
        {
          "address": "F179",
          "column": "F",
          "field": "三级目录",
          "value": "锂电池原型样机铁路订舱与出运资料复核",
          "chars": 18,
          "hasNewlines": false,
          "preview": "锂电池原型样机铁路订舱与出运资料复核"
        },
        {
          "address": "G179",
          "column": "G",
          "field": "任务概括",
          "value": "复核未完成UN38.3的锂电池原型样机及备用电池经中欧班列出运时的申报属性、型号证据、包装标记、鉴定资料和承运确认，形成有边界的订舱放行意见与补件台账。",
          "chars": 76,
          "hasNewlines": false,
          "preview": "复核未完成UN38.3的锂电池原型样机及备用电池经中欧班列出运时的申报属性、型号证据、包装标记、鉴定资料和承运确认，形成有边界的订舱放行意见与补件台账。"
        },
        {
          "address": "H179",
          "column": "H",
          "field": "标注专家工作年限",
          "value": "7年",
          "chars": 2,
          "hasNewlines": false,
          "preview": "7年"
        },
        {
          "address": "I179",
          "column": "I",
          "field": "人类完成时间",
          "value": "16h",
          "chars": 3,
          "hasNewlines": false,
          "preview": "16h"
        },
        {
          "address": "J179",
          "column": "J",
          "field": "相关附件",
          "value": "附件一_消费型锂电池货物铁路运输指导意见.html；附件二_铁路危险货物运输安全监督管理规定.html；附件三_铁路货物运输规则_2026.pdf；附件四_国际货协危险货物规则2025修改通知.html；附件五_国际货协危险货物规则2025修改事项.pdf；附件六_B3原型样机订舱事实与缺件清单_截至2026-07-10.json",
          "chars": 166,
          "hasNewlines": false,
          "preview": "附件一_消费型锂电池货物铁路运输指导意见.html；附件二_铁路危险货物运输安全监督管理规定.html；附件三_铁路货物运输规则_2026.pdf；附件四_国际"
        },
        {
          "address": "K179",
          "column": "K",
          "field": "附件格式",
          "value": "html, pdf, json",
          "chars": 15,
          "hasNewlines": false,
          "preview": "html, pdf, json"
        },
        {
          "address": "L179",
          "column": "L",
          "field": "附件内容",
          "value": "附件一：《国铁运输监〔2023〕26号，2023年10月11日》（文件：附件一_消费型锂电池货物铁路运输指导意见.html），属于官方中文资料，用于核对：作为国内铁路段的结构化资料清单和初筛框架，核对适用范围、UN38.3、运输条件鉴定、包装检验、申报记载、包件标记及不予运输情形。 来源：https://www.nra.gov.cn/jglz/ysjg/fgys/202311/t20231102_343599.shtml。中文摘要：铁路运输时，可由承托双方按照本指导意见及铁路货物运输有关规定办理；通过中欧班列等国际铁路联运时，还应当符合国际联运有关规定。；托运前，托运人应当向铁路运输企业提交产品安全性测试报告、铁路运输条件鉴定报告、铁路运输包装检验报告、安全承诺和应急处置措施，并对所提供材料的真实性和锂电池货物安全性负责。；除装在设备（包括电路板）上的纽扣电池外，2003年6月30日以后制造的电池或电池组，其制造商和出厂后的销售商应提供《关于危险货物运输的建议书 试验和标准手册》（第7修订版）第3部分第38.3节第38.3.5段规定的试验简介。；对于锂离子电池组，瓦特-小时的额定值小于或等于100Wh。锂离子电池组应在外壳上标明瓦特-小时的额定值。 证据边界：该指导意见明确针对消费型锂电池国内铁路运输，并明确中欧班列还须符合国际联运规定。98Wh只是一项阈值线索，不能单独证明B3原型样机可作为普通货物订舱；也不能用B2报告证明B3已完成测试。\n附件二：《交通运输部令2022年第24号，自2022年12月1日起施行；国家铁路局页面标示时效性为“有效”》（文件：附件二_铁路危险货物运输安全监督管理规定.html），属于官方中文资料，用于核对：核对危险性质不明、新品名或新包装、办理站条件、包装要求、托运人如实申报、承运安全检查和证明材料留存等底线。 来源：https://www.nra.gov.cn/xxgk/gkml/ztjg/gfzd/bmgz/202210/t20221021_338669.shtml。中文摘要：（二）危险性质不明、可能存在安全隐患的物品；；（二）包装能够抗御运输、储存和装卸过程中正常的冲击、振动、堆码和挤压，并便于装卸和搬运；；托运人应当按照铁路危险货物品名表确定危险货物的类别、项别、品名、铁危编号、包装等，遵守相关特殊规定要求。；不得承运未接受安全检查的货物，不得承运不符合安全规定、可能危害铁路运输安全的货物。 证据边界：该规定给出国内铁路危货管理底线，但不直接替B3电池作分类，不提供中欧班列沿线国家的接受结论，也不等同于具体承运人的订舱细则。\n附件三：《交通运输部令2026年第2号，2026年2月3日公布，自2026年5月1日起施行》（文件：附件三_铁路货物运输规则_2026.pdf），属于官方中文资料，用于核对：采用2026年现行铁路货运基础规则，核对危险货物技术要求、运单信息、托运文件真实性、凭证提交、实名安全查验和承运拒收边界。 来源：https://xxgk.mot.gov.cn/gz/202602/W020260226551364108827.pdf。中文摘要：铁路运输危险货物，应当遵守法律、行政法规、规章和国家铁路局有关规定，并符合有关技术要求。；托运人应当如实填写托运相关信息，对其在货物运单及所附物品清单等填记事项的真实性和完整性负责。；托运人未按照规定提供有效文件的，铁路运输企业不得受理。；铁路运输企业不得运输托运人拒绝安全检查的货物和不符合安全规定、可能危害铁路运输安全的货物。 证据边界：这是截至题目日期已施行的境内铁路货运基础规则，不含B3型号技术判断和国际联运各段的专项接受条件；不能据此跳过危险货物或原型品专项规则。\n附件四：《2025年5月16日发布，所附修改和补充事项自2025年7月1日起生效》（文件：附件四_国际货协危险货物规则2025修改通知.html），属于官方中文资料，用于核对：确认附件五修改文本的官方发布主体与生效时间，建立题目采用国际联运更新口径的版本证据。 来源：https://www.nra.gov.cn/jglz/ysjg/fgys/202505/t20250516_348874.shtml。中文摘要：接铁路合作组织2025年1月27日第II-2-25/JA号通知，铁组委员会委员（2024年）第6次定期会议（2024年11月18日）决议通过了国际货协附件2《危险货物运送规则》及《为履行国际货协附件2的要求而另行适用的技术标准文件清单》的修改和补充事项，自2025年7月1日起生效，现予公布。 证据边界：该通知只证明所附修改文本的发布和生效，不是国际货协附件2的完整合并文本，也不证明具体班列、过境国、换装站或承运人已经接受本票原型样机。\n附件五：《铁组委员会第II-2-25/JA号信函附件1，自2025年7月1日起生效》（文件：附件五_国际货协危险货物规则2025修改事项.pdf），属于官方中文资料，用于核对：核对国际铁路联运对不超过100个电池或电池组的生产运行产品、为试验运输的未投产原型品及相应包装规范的更新文字。 来源：https://www.nra.gov.cn/xwzx/jlhz/gjty/202505/P020250516455543627607.pdf。中文摘要：不超过100个电池或电池组的生产运行所产生的电池或电池组，或为试验而运输的电池或电池组的尚未投产的原型物品，应符合2.2.9.1.7.1的规定，但a）、e）（七）、f）（三）（如适用）、f）（四）（如适用）和g）除外。；“为试验而运输”包括但不限于《试验和标准手册》第三部分38.3中小节“集成试验和产品性能试验”中所述的试验。；这些电池和电池组应根据情况，按4.1.4.1中的包装规范P910或4.1.4.3中的包装规范LP905进行包装。 证据边界：附件五是修改和补充事项而非完整合并规则。SP 310提示原型电池存在专项路径，不等于B3样机自动获准承运；装在设备中的电池与单独备用电池应分开判断，并取得当前完整规则、路线参与方和承运人的书面确认。\n附件六：《截至2026-07-10的题设货物、路线、包件和资料状态底表》（文件：附件六_B3原型样机订舱事实与缺件清单_截至2026-07-10.json），属于官方中文资料，用于核对：直接提供本票货物的型号、数量、额定能量、装在设备中或单独运输的形态、拟申报品名、4箱草图状态、B2与B3证据不匹配以及各项缺件，供docx和xlsx逐项引用。 来源：https://www.nra.gov.cn/jglz/ysjg/fgys/202311/t20231102_343599.shtml。中文摘要：截至2026-07-10，题设证据不足以支持将整票按普通电子产品提交订舱；应先完成B3型号证据、两类货物包装路径和路线参与方书面确认。 证据边界：该JSON是题设信息的可追溯整理，不是外部真实企业档案，也不是UN38.3报告、试验简介、运输条件鉴定、包装检验、安全承诺、应急措施或承运批准。\n总边界：五份公开资料和一份题设业务底表可以支持对本票型号、数量、申报属性、测试/鉴定资料、包装与标记、国内和国际规则分流以及订舱阻断项进行预审；题设底表不是外部证明，全部附件仍不能证明B3与B2型号等同，不能替代UN38.3报告或试验简介、铁路运输条件鉴定、包装检验报告，也不能替代2026年7月具体班列、过境国、换装站、境外铁路和承运人的最新书面接受条件。",
          "chars": 3111,
          "hasNewlines": true,
          "preview": "附件一：《国铁运输监〔2023〕26号，2023年10月11日》（文件：附件一_消费型锂电池货物铁路运输指导意见.html），属于官方中文资料，用于核对：作为国"
        },
        {
          "address": "M179",
          "column": "M",
          "field": "产物格式",
          "value": "docx, xlsx",
          "chars": 10,
          "hasNewlines": false,
          "preview": "docx, xlsx"
        },
        {
          "address": "N179",
          "column": "N",
          "field": "产物内容",
          "value": "docx面向研发、供应链和订舱代理，先给出是否支持按“普通电子产品”提交的结论，再分别审查24台内装B3电池的样机和8块单独备用电池，拆开国内铁路段与国际联运段，形成事实表、型号/报告对应、规则适用路径、包装和标记缺口、四档放行矩阵、向承运人/主管机关的书面确认问题及最终责任边界。xlsx至少设置“货物与型号”“证据对应”“包件检查”“材料缺口”“路线/承运确认”五个工作表；逐行记录货物形态、数量、Wh、型号版本、UN38.3文件对应型号、原型状态、拟申报品名、国内铁危编号待确认项、国际规则线索、包装指令待确认项、短路/误启动防护、包件重量、标记、现有证据、缺件、责任人、截止时间、承运书面回复和放行状态。验收时不得因98Wh低于100Wh就把整票写成普通货物，也不得把SP 310写成自动豁免或最终承运批准。",
          "chars": 358,
          "hasNewlines": false,
          "preview": "docx面向研发、供应链和订舱代理，先给出是否支持按“普通电子产品”提交的结论，再分别审查24台内装B3电池的样机和8块单独备用电池，拆开国内铁路段与国际联运段"
        },
        {
          "address": "O179",
          "column": "O",
          "field": "做题关键步骤",
          "value": "1. 以附件六截至2026-07-10的题设业务底表固化本票事实，把24台内装B3电池的运动相机样机与8块单独备用B3电池拆成两类货物，不混用结论，也不把题设底表当成第三方证明。\n2. 建立型号—文件对应表，核对B2的UN38.3报告和试验简介是否明确覆盖B3；没有同一型号或技术等同性证据时标为不匹配，不自行外推。\n3. 用附件一判断消费型锂电池国内铁路段的适用范围、Wh阈值、特殊规定78/79线索及特殊规定72禁运情形，并保留“中欧班列还须符合国际联运规定”的边界。\n4. 按附件一的五项清单核对产品安全性测试报告、运输条件鉴定、包装检验报告、安全承诺和应急处置措施，逐项记录缺件与责任人。\n5. 用附件二核对危险性质未明、新包装/改变包装、办理站、如实申报、包装性能、安全检查和证明材料要求，识别不能先按普通电子产品占舱的阻断点。\n6. 用附件三核对2026年现行货运规则下运单及物品清单真实性、有效证明文件、包装、实名查验和铁路企业不得受理/不得运输的边界。\n7. 用附件四确认国际货协附件2修改文本的官方来源和2025年7月1日生效时间，不把旧版本口径直接带入2026年7月订舱。\n8. 用附件五SP 310识别未投产原型电池的专项规则线索和P910/LP905包装提示，同时注明附件只是修改文本，不能脱离完整合并规则使用。\n9. 对4箱混装草图做包件级复核，逐箱列内装设备数、备用电池数、额定能量、总重、短路防护、误启动防护、内外包装、跌落/堆码证据和标记状态。\n10. 将每一判断归入“可按现方案提交、补件后再提交、改走危货/原型品路径、暂停出货并确认”四档，并把依据、缺口和解锁条件写在同一行。\n11. 起草给班列平台、境内外承运人和相关主管机关的书面确认问题，至少覆盖申报品名/编号、原型规则适用、包装指令、沿线国家接受、换装/转运限制及所需批准文件。\n12. 完成docx和xlsx交叉复核：结论、货物数量、型号、Wh、包件、缺件和状态一致；所有未获书面证实的事项均写成待确认，不替承运人或主管机关作最终批准。",
          "chars": 866,
          "hasNewlines": true,
          "preview": "1. 以附件六截至2026-07-10的题设业务底表固化本票事实，把24台内装B3电池的运动相机样机与8块单独备用B3电池拆成两类货物，不混用结论，也不把题设底"
        },
        {
          "address": "P179",
          "column": "P",
          "field": "标注专家姓名",
          "value": "沈礼",
          "chars": 2,
          "hasNewlines": false,
          "preview": "沈礼"
        }
      ]
    },
    {
      "dataRow": 4,
      "sheetRow": 180,
      "title": "预审岛津 LC-20A 高效液相色谱系统的到货点验、安装条件、技术性能和付款证据，判断当前能否签署验收合格并启动尾款。",
      "updates": [
        {
          "address": "A180",
          "column": "A",
          "field": "UID",
          "value": "沈礼_7.10_06",
          "chars": 10,
          "hasNewlines": false,
          "preview": "沈礼_7.10_06"
        },
        {
          "address": "B180",
          "column": "B",
          "field": "题目",
          "value": "分析测试中心新购的一套岛津 LC-20A 高效液相色谱系统已经运到实验楼，供货商希望本周开箱、下周安装，并口头说验收签字后就能申请尾款。资产管理员目前只收到箱数照片和安装日期，项目合同正文及技术附件、供应商响应文件、装箱单、序列号清单、质量证明书、场地确认表、安装调试记录、性能测试原始数据和培训签到表都还没归档。请先按附件做一次付款前技术验收预审：把可参考的配置和参数整理成核对基线，区分到货点验、安装前置条件、安装调试、性能实测和付款触发证据，明确哪些缺口会阻断开箱签字、安装、验收合格或尾款申请。最终给中心主任一份可编辑的验收预审意见和一张参数/证据台账；公共采购公示、外校流程和空白模板只能作为核对框架，不能写成本项目真实合同、实测数据或已经验收合格。",
          "chars": 330,
          "hasNewlines": false,
          "preview": "分析测试中心新购的一套岛津 LC-20A 高效液相色谱系统已经运到实验楼，供货商希望本周开箱、下周安装，并口头说验收签字后就能申请尾款。资产管理员目前只收到箱数"
        },
        {
          "address": "C180",
          "column": "C",
          "field": "任务类型",
          "value": "L2 流程型",
          "chars": 6,
          "hasNewlines": false,
          "preview": "L2 流程型"
        },
        {
          "address": "D180",
          "column": "D",
          "field": "一级目录",
          "value": "投资战略、专业服务与企业经营",
          "chars": 14,
          "hasNewlines": false,
          "preview": "投资战略、专业服务与企业经营"
        },
        {
          "address": "E180",
          "column": "E",
          "field": "二级目录",
          "value": "科研采购与实验室运营",
          "chars": 10,
          "hasNewlines": false,
          "preview": "科研采购与实验室运营"
        },
        {
          "address": "F180",
          "column": "F",
          "field": "三级目录",
          "value": "高效液相色谱仪到货验收与付款前技术核对",
          "chars": 19,
          "hasNewlines": false,
          "preview": "高效液相色谱仪到货验收与付款前技术核对"
        },
        {
          "address": "G180",
          "column": "G",
          "field": "任务概括",
          "value": "预审岛津 LC-20A 高效液相色谱系统的到货点验、安装条件、技术性能和付款证据，判断当前能否签署验收合格并启动尾款。",
          "chars": 59,
          "hasNewlines": false,
          "preview": "预审岛津 LC-20A 高效液相色谱系统的到货点验、安装条件、技术性能和付款证据，判断当前能否签署验收合格并启动尾款。"
        },
        {
          "address": "H180",
          "column": "H",
          "field": "标注专家工作年限",
          "value": "6年",
          "chars": 2,
          "hasNewlines": false,
          "preview": "6年"
        },
        {
          "address": "I180",
          "column": "I",
          "field": "人类完成时间",
          "value": "14h",
          "chars": 3,
          "hasNewlines": false,
          "preview": "14h"
        },
        {
          "address": "J180",
          "column": "J",
          "field": "相关附件",
          "value": "附件一_华东理工大学LC20A采购技术参数公示.html；附件二_岛津LC20A安装准备条件.pdf；附件三_中国地质大学大型仪器设备验收工作流程.pdf；附件四_中国传媒大学项目到货验收申请表.xlsx；附件五_华南理工大学仪器设备开箱与点验货记录.docx；附件六_华南理工大学进口仪器设备购置合同模板.docx",
          "chars": 158,
          "hasNewlines": false,
          "preview": "附件一_华东理工大学LC20A采购技术参数公示.html；附件二_岛津LC20A安装准备条件.pdf；附件三_中国地质大学大型仪器设备验收工作流程.pdf；附件"
        },
        {
          "address": "K180",
          "column": "K",
          "field": "附件格式",
          "value": "html, pdf, xlsx, docx",
          "chars": 21,
          "hasNewlines": false,
          "preview": "html, pdf, xlsx, docx"
        },
        {
          "address": "L180",
          "column": "L",
          "field": "附件内容",
          "value": "附件一：《附件一_华东理工大学LC20A采购技术参数公示.html》（文件：附件一_华东理工大学LC20A采购技术参数公示.html），属于官方中文资料，用于核对：提取 LC-20A 公开采购中的系统组成、泵、自动进样器、柱温箱、检测器和工作站参数，作为建立技术核对矩阵的参考样例。 来源：https://hgxy.ecust.edu.cn/_t58/2020/1030/c1176a117977/page.htm。中文摘要：流速范围：0.001-10.0ml/min；压力范围：1-40 MPa；流速精确度：≤0.06% RSD。 证据边界：这是华东理工大学另一采购项目的公示，不是本项目的合同、招标文件或供应商承诺；参数只能标为公开参考值，最终验收基线必须回到本项目已签合同及其技术附件。\n附件二：《附件二_岛津LC20A安装准备条件.pdf》（文件：附件二_岛津LC20A安装准备条件.pdf），属于官方中文资料，用于核对：核对 LC-20A 安装前的温湿度、空间、电源、接地、气体、排气、废液瓶和维护耗材准备条件。 来源：https://www.shimadzu.com.cn/sites/shimadzu.com.cn/files/upload/ser-install/lc-20a.pdf。中文摘要：温度4～35℃；220V±10%（电源应含有地线）。 证据边界：该资料是厂商同型号安装准备文件且形成时间较早，只能辅助现场预检；应另向本次供货商取得当前配置对应的安装确认书，不能凭该 PDF 证明实验室现场已经达标。\n附件三：《附件三_中国地质大学大型仪器设备验收工作流程.pdf》（文件：附件三_中国地质大学大型仪器设备验收工作流程.pdf），属于官方中文资料，用于核对：建立大型仪器技术验收资料清单，覆盖论证、申报、招投标、合同、开箱、安装调试、自检、验收、开放管理和使用维护记录。 来源：https://sbc.cug.edu.cn/__local/F/4D/0A/E09F56108B7ECD7C7835DAA4E9B_8360CC77_4657F.pdf。中文摘要：开箱检验记录：供货商与使用单位按合同清点。 证据边界：流程和运行期限属于该校制度，不能直接套用为本项目的强制时限；本题仅借其材料清单识别证据缺口，实际程序须核对采购单位自己的有效制度。\n附件四：《附件四_中国传媒大学项目到货验收申请表.xlsx》（文件：附件四_中国传媒大学项目到货验收申请表.xlsx），属于官方中文资料，用于核对：提供结构化到货申请字段，用于检查项目名称、负责人、单位、地点、合同日期、工期、中标公司、价格、采购方式、项目简介和到货情况是否完整。 来源：https://lemd.cuc.edu.cn/_upload/article/files/09/34/5407433b4a00a0bad66f2c9ed069/cb7a3340-81af-48c3-8bff-0b52261fc3b4.xlsx。中文摘要：到货情况（请简述到货情况）。 证据边界：这是未填写的外校空白表，只能用于设计本题 xlsx 的字段，不是本项目到货事实、审批意见或验收申请。\n附件五：《附件五_华南理工大学仪器设备开箱与点验货记录.docx》（文件：附件五_华南理工大学仪器设备开箱与点验货记录.docx），属于官方中文资料，用于核对：核对开箱参与人、合同和装箱单依据、包装和外观、规格型号、质量证明、随机资料、件数差异、异常情况及签字留痕。 来源：https://www2.scut.edu.cn/_upload/article/files/4e/21/929439f741d88a95910737b4b308/7b4b61bc-dfd3-401f-a458-51660503fdc6.docx。中文摘要：开箱点验货以合同和装箱单为依据。 证据边界：这是空白点验模板，不能替代本项目经购置人、设备员、供货商及相关人员签字确认的真实记录，也不能证明实物型号、数量或外观已经核对。\n附件六：《附件六_华南理工大学进口仪器设备购置合同模板.docx》（文件：附件六_华南理工大学进口仪器设备购置合同模板.docx），属于官方中文资料，用于核对：提供设备清单、付款、质量保证、检验验收、风险转移、售后和违约条款的核对框架，提示验收与付款触发条件必须回到签署合同。 来源：https://www2.scut.edu.cn/_upload/article/files/4e/21/929439f741d88a95910737b4b308/40deec8b-933f-456c-9e04-61c2f1f7f0ec.docx。中文摘要：验收标准按照本合同及采购文件中列明的技术参数、规格、性能指标等执行。 证据边界：这是外校空白合同模板，不是本项目签署合同；不得据此推定付款比例、验收主体、风险转移、质保期限或违约责任。本项目合同缺失时只能判为付款条件待核。\n总边界：六份资料分别提供同型号公开采购参数、厂商安装条件、技术验收资料清单、到货申请字段、开箱点验字段以及合同验收/付款条款框架。使用时必须建立证据等级：本项目已签合同及附件、供应商投标响应和承诺、签字盖章的开箱/安装/测试记录优先；公开采购公示、外校流程和空白模板仅用于搭建核对清单。当前缺少本项目合同、装箱单、序列号、质量证明、场地确认、安装调试、性能测试原始数据、培训记录和签章验收报告，不能据此认定设备已经满足合同参数、验收合格或具备付款条件。",
          "chars": 2291,
          "hasNewlines": true,
          "preview": "附件一：《附件一_华东理工大学LC20A采购技术参数公示.html》（文件：附件一_华东理工大学LC20A采购技术参数公示.html），属于官方中文资料，用于核"
        },
        {
          "address": "M180",
          "column": "M",
          "field": "产物格式",
          "value": "docx, xlsx",
          "chars": 10,
          "hasNewlines": false,
          "preview": "docx, xlsx"
        },
        {
          "address": "N180",
          "column": "N",
          "field": "产物内容",
          "value": "docx 面向中心主任、资产管理员和采购经办人，写明预审范围、证据等级、到货点验结果框架、安装条件核对、技术参数测试计划、当前阻断项、补件责任人、分阶段建议和付款结论边界。xlsx 建立可追溯参数/证据台账，至少含阶段、系统模块、核对项、合同基线、公开参考值、验收方法、原始记录位置、实测值、允许偏差、结果、证据等级、缺口、责任人、截止日期、复核人和付款影响；另设配置点验、场地条件、资料清单和问题闭环工作表。结论只能使用“可开箱点验”“可安排安装”“待技术验收”“暂缓验收/付款”等受证据约束的状态，不得把公共资料中的数值复制成实际合同值或实测值。",
          "chars": 275,
          "hasNewlines": false,
          "preview": "docx 面向中心主任、资产管理员和采购经办人，写明预审范围、证据等级、到货点验结果框架、安装条件核对、技术参数测试计划、当前阻断项、补件责任人、分阶段建议和付"
        },
        {
          "address": "O180",
          "column": "O",
          "field": "做题关键步骤",
          "value": "1. 核验六份附件的发布主体、来源链接、格式、文件哈希和可解析内容，记录每份资料可支持与不可支持的范围。\n2. 建立证据等级：本项目签署合同及技术附件优先，其次为供应商响应与承诺、签章记录和原始测试数据；公开采购公示、厂商通用资料及外校模板仅作参考。\n3. 从华东理工大学采购公示提取 LC-20A 的系统配置以及泵、进样器、柱温箱、检测器、工作站参数，全部标记为公开参考值，等待本项目合同基线替换或确认。\n4. 从岛津安装准备条件整理温湿度、空间、电源、接地、气体、排气、废液和耗材检查项，并要求本次供货商提供当前配置对应的安装确认书。\n5. 按照开箱点验模板核对包装、箱数、设备名称、品牌型号、序列号、配件、质量证明和随机资料，合同或装箱单缺失时不得把箱数照片认定为点验完成。\n6. 把流程拆成到货点验、场地预检、安装调试、技术性能测试、问题整改、正式验收和付款申请，避免用一个“验收通过”状态覆盖不同阶段。\n7. 使用到货申请表字段整理项目名称、负责人、单位、地点、合同日期、供货商、价格、采购方式和到货说明，空缺信息进入补件台账。\n8. 为泵流速/压力/梯度、进样体积与重复性、交叉污染、柱温范围与稳定性、检测器波长/噪声/漂移、软件控制和数据导出建立逐项测试矩阵。\n9. 逐项填写验收方法、使用标准物质或工具、测试次数、原始数据文件、计算公式、合同限值、实测值、偏差和签字人；没有原始记录的项目保持“未测试”，不得估算通过。\n10. 参照大型仪器验收资料清单核对论证、采购、招投标、合同、开箱、安装调试、自检、验收、开放管理和维护记录，同时标注外校流程不能直接替代本单位制度。\n11. 从合同模板提取付款与验收的关系作为审查问题，转而查找本项目实际合同中的付款比例、验收标准、验收主体、风险转移、质保和违约条款。\n12. 按证据状态给出分阶段建议：材料足够才可开箱点验；场地确认后才安排安装；合同指标与原始测试均闭环后才提交正式验收；签章报告和实际付款条款齐备前暂缓尾款。\n13. 生成 docx 预审意见和 xlsx 参数/证据台账，并交叉检查附件编号、参考值、缺口、责任人、阶段状态和付款影响，确认没有将公共模板或其他项目参数写成本项目事实。",
          "chars": 928,
          "hasNewlines": true,
          "preview": "1. 核验六份附件的发布主体、来源链接、格式、文件哈希和可解析内容，记录每份资料可支持与不可支持的范围。 2. 建立证据等级：本项目签署合同及技术附件优先，其次"
        },
        {
          "address": "P180",
          "column": "P",
          "field": "标注专家姓名",
          "value": "沈礼",
          "chars": 2,
          "hasNewlines": false,
          "preview": "沈礼"
        }
      ]
    }
  ]
}
